nonebot_plugin_batch_withdrawal/__init__.py
nonebot_plugin_batch_withdrawal-0.0.6.dist-info/LICENSE
nonebot_plugin_batch_withdrawal-0.0.6.dist-info/METADATA
nonebot_plugin_batch_withdrawal-0.0.6.dist-info/WHEEL
nonebot_plugin_batch_withdrawal-0.0.6.dist-info/top_level.txt
nonebot_plugin_batch_withdrawal-0.0.6.dist-info/RECORD
