Metadata-Version: 2.1
Name: nonebot-plugin-batch-withdrawal
Version: 0.0.6
Summary: 批量撤回
Requires-Python: <4.0,>=3.9
License-File: LICENSE
Requires-Dist: nonebot-plugin-alconna >=0.52.2
Requires-Dist: nonebot-plugin-localstore >=0.7.1
Requires-Dist: nonebot-adapter-onebot >=2.4.5
Requires-Dist: nonebot2 >=2.3.3
Requires-Dist: aiosqlite >=0.20.0
